{
    "version": "0.2",
    "language": "fr",
    "ignorePaths": ["mkdocs.yml", "mkdocs.dev.yml"],
    "dictionaries": ["fr-fr"],
    "import": ["@cspell/dict-fr-fr/cspell-ext.json"],
    "dictionaryDefinitions": [],
    "words": [
        "mkdocs",
        "Arété",
        "Absyr",
        "Ethéria",
        "Éthéria",
        "FATE",
        "etheria",
        "systeme",
        "mecaniques",
        "geographie",
        "requirements",
        "venv",
        "PYTHONPATH",
        "MONTYPE",
        "REGLE",
        "TRESOR",
        "Obsidian",
        "obsidian",
        "desactive",
        "accentuees",
        "aligned",
        "delimiter",
        "compel",
        "compeller",
        "stunt",
        "Stunts",
        "akrasia",
        "phronèsis",
        "homonoia",
        "mêmeté",
        "capabilités",
        "Alasdair",
        "Intyre",
        "Amartya",
        "Nozick",
        "Rawls",
        "Ricœur",
        "Hutcheson",
        "Jarvis",
        "Béotie",
        "Lycurgue",
        "Numa",
        "Pompilius",
        "Solon",
        "Reasons",
        "Persons",
        "Story",
        "Philosophy",
        "Anarchy",
        "Utopia",
        "Abortion",
        "Keep",
        "operativus",
        "Théostrate",
        "Théséis",
        "Éleuthéra",
        "Élégéia",
        "Silys",
        "Kharôn",
        "Naüm",
        "Civira",
        "Halden",
        "Eudaimon",
        "Éléon",
        "d'Eudaimon",
        "d'Éléon",
        "d'Aphélion",
        "Luhen",
        "Alea",
        "d'Alve",
        "Eudémos",
        "d'arétê",
        "Sophrosynê",
        "sophrosynê",
        "Camüs",
        "d'Omelas",
        "Justomètre",
        "Maximisants",
        "Delié",
        "Juma",
        "Ariadnos",
        "Seraphia",
        "Obliquus",
        "Clavéria",
        "Équitania",
        "Sophon",
        "Éthérialistes",
        "ruff",
        "precises",
        "reconcevoir"
    ],
    "ignoreWords": []
}
